clirainbow/__init__.py
clirainbow/__main__.py
clirainbow/clirainbow.py
clirainbow/colors.py
clirainbow/formatter.py
clirainbow-1.2.0.dist-info/DESCRIPTION.rst
clirainbow-1.2.0.dist-info/METADATA
clirainbow-1.2.0.dist-info/RECORD
clirainbow-1.2.0.dist-info/WHEEL
clirainbow-1.2.0.dist-info/metadata.json
clirainbow-1.2.0.dist-info/top_level.txt
