Metadata-Version: 2.0
Name: clirainbow
Version: 1.2.0
Summary: Easily print colored text.
Home-page: https://github.com/mlevesquedion/clirainbow
Author: Michaël Lévesque-Dion
Author-email: mlevesquedion@gmail.com
License: MIT
Platform: UNKNOWN
Classifier: License :: OSI Approved :: MIT License
Classifier: Programming Language :: Python :: 3
Requires-Dist: colorama
